firefly_iii_client/__init__.py
firefly_iii_client/api_client.py
firefly_iii_client/configuration.py
firefly_iii_client/exceptions.py
firefly_iii_client/model_utils.py
firefly_iii_client/rest.py
firefly_iii_client/api/__init__.py
firefly_iii_client/api/about_api.py
firefly_iii_client/api/accounts_api.py
firefly_iii_client/api/attachments_api.py
firefly_iii_client/api/autocomplete_api.py
firefly_iii_client/api/available_budgets_api.py
firefly_iii_client/api/bills_api.py
firefly_iii_client/api/budgets_api.py
firefly_iii_client/api/categories_api.py
firefly_iii_client/api/charts_api.py
firefly_iii_client/api/configuration_api.py
firefly_iii_client/api/currencies_api.py
firefly_iii_client/api/currency_exchange_rates_api.py
firefly_iii_client/api/data_api.py
firefly_iii_client/api/import_api.py
firefly_iii_client/api/insight_api.py
firefly_iii_client/api/links_api.py
firefly_iii_client/api/object_groups_api.py
firefly_iii_client/api/piggy_banks_api.py
firefly_iii_client/api/preferences_api.py
firefly_iii_client/api/recurrences_api.py
firefly_iii_client/api/rule_groups_api.py
firefly_iii_client/api/rules_api.py
firefly_iii_client/api/search_api.py
firefly_iii_client/api/summary_api.py
firefly_iii_client/api/tags_api.py
firefly_iii_client/api/transactions_api.py
firefly_iii_client/api/users_api.py
firefly_iii_client/api/webhooks_api.py
firefly_iii_client/apis/__init__.py
firefly_iii_client/model/__init__.py
firefly_iii_client/model/account.py
firefly_iii_client/model/account_array.py
firefly_iii_client/model/account_read.py
firefly_iii_client/model/account_role_property.py
firefly_iii_client/model/account_search_field_filter.py
firefly_iii_client/model/account_single.py
firefly_iii_client/model/account_store.py
firefly_iii_client/model/account_type_filter.py
firefly_iii_client/model/account_type_property.py
firefly_iii_client/model/account_update.py
firefly_iii_client/model/attachable_type.py
firefly_iii_client/model/attachment.py
Firefly_III_API_Python_Client-1.5.6.post2.dist-info/LICENSE
Firefly_III_API_Python_Client-1.5.6.post2.dist-info/METADATA
Firefly_III_API_Python_Client-1.5.6.post2.dist-info/WHEEL
Firefly_III_API_Python_Client-1.5.6.post2.dist-info/top_level.txt
Firefly_III_API_Python_Client-1.5.6.post2.dist-info/RECORD
