Metadata-Version: 2.1
Name: Firefly-III-API-Python-Client
Version: 1.5.6.post2
Summary: Firefly III API Python Client
Home-page: https://github.com/ms32035/firefly-iii-client
Author: Marcin Szymanski, revised Xavier V.
Author-email: ms32035@gmail.com
License: AGPLv3
Keywords: OpenAPI,OpenAPI-Generator,Firefly III API Python Client
Requires-Python: >=3.6
License-File: LICENSE
Requires-Dist: urllib3 (>=1.25.3)
Requires-Dist: python-dateutil
